{
    "AssemblyFilePath": "./bin/Debug/net6.0/Guilded.Base.dll",
    "OutputDirectoryPath": "../Documentation/Guilded.Base",
    "GeneratedAccessModifiers": "Public,ProtectedInternal,Protected",
    "GeneratedPages": "Assembly,Types,Members,Namespaces",

    "FileNameFactory": "Name",
    "Markdown.RemoveFileExtensionFromUrl": true,
    "LinksOutputFilePath": "../Documentation/Guilded.Base.link",

    "AssemblyPageName": "index",
    "AssemblyDocItem": {
        "Sections": [
            "TableOfContents"
        ],
        "Markdown.TableOfContentsModes": "IncludeKind"
    },
    "NamespaceDocItem": {
        "Sections": [
            "FrontMatterStart",
            "FrontMatterEnd",
            "Title",
            "TableOfContents"
        ],
        "Markdown.TableOfContentsModes": "IncludeKind,IncludeSummaryWithNewLine"
    },
    "ClassDocItem": {
        "Sections": [
            "FrontMatterStart",
            "summary",
            "FrontMatterEnd",
            "Title",
            "ModifiedHeader",
            "summary",
            "Definition",
            "Inheritance",
            "Implement",
            "Derived",
            "TypeParameters",
            "remarks",
            "example",
            "Constructors",
            "Fields",
            "Properties",
            "Events",
            "Methods",
            "Operators",
            "Classes",
            "Structs",
            "Interfaces",
            "Enums",
            "Delegates",
            "seealso"
        ]
    },
    "EnumDocItem": {
        "Sections": [
            "FrontMatterStart",
            "summary",
            "FrontMatterEnd",
            "Title",
            "ModifiedHeader",
            "summary",
            "Definition",
            "remarks",
            "example",
            "EnumFields",
            "Classes",
            "Structs",
            "Interfaces",
            "Enums",
            "Delegates",
            "seealso"
        ]
    },
    "InterfaceDocItem": {
        "Sections": [
            "FrontMatterStart",
            "summary",
            "FrontMatterEnd",
            "Title",
            "ModifiedHeader",
            "summary",
            "Definition",
            "Implement",
            "Derived",
            "TypeParameters",
            "remarks",
            "example",
            "Fields",
            "Properties",
            "Events",
            "Methods",
            "Explicitinterfaceimplementations",
            "Classes",
            "Structs",
            "Interfaces",
            "Enums",
            "Delegates",
            "seealso"
        ]
    },
    "StructDocItem": {
        "Sections": [
            "FrontMatterStart",
            "summary",
            "FrontMatterEnd",
            "Title",
            "ModifiedHeader",
            "summary",
            "Definition",
            "Implement",
            "TypeParameters",
            "remarks",
            "example",
            "Constructors",
            "Fields",
            "Properties",
            "Events",
            "Methods",
            "Operators",
            "Classes",
            "Structs",
            "Interfaces",
            "Enums",
            "Delegates",
            "seealso"
        ]
    },
    "DelegateDocItem": {
        "Sections": [
            "FrontMatterStart",
            "summary",
            "FrontMatterEnd",
            "Title",
            "ModifiedHeader",
            "summary",
            "Definition",
            "TypeParameters",
            "Parameters",
            "remarks",
            "example",
            "returns",
            "seealso"
        ]
    },

    "ConstructorDocItem": {
        "Sections": [
            "FrontMatterStart",
            "summary",
            "FrontMatterEnd",
            "Title",
            "ModifiedHeader",
            "summary",
            "Definition",
            "remarks",
            "example",
            "Parameters",
            "exception",
            "returns",
            "seealso"
        ]
    },
    "FieldDocItem": {
        "Sections": [
            "FrontMatterStart",
            "summary",
            "FrontMatterEnd",
            "Title",
            "ModifiedHeader",
            "summary",
            "Definition",
            "remarks",
            "example",
            "value",
            "seealso"
        ]
    },
    "PropertyDocItem": {
        "Sections": [
            "FrontMatterStart",
            "summary",
            "FrontMatterEnd",
            "Title",
            "ModifiedHeader",
            "summary",
            "Definition",
            "remarks",
            "example",
            "exception",
            "returns",
            "value",
            "seealso"
        ]
    },
    "MethodDocItem": {
        "Sections": [
            "FrontMatterStart",
            "summary",
            "FrontMatterEnd",
            "Title",
            "ModifiedHeader",
            "summary",
            "Definition",
            "TypeParameters",
            "Parameters",
            "remarks",
            "example",
            "exception",
            "returns",
            "seealso"
        ]
    },
    "EventDocItem": {
        "Sections": [
            "FrontMatterStart",
            "summary",
            "FrontMatterEnd",
            "Title",
            "ModifiedHeader",
            "summary",
            "Definition",
            "remarks",
            "example",
            "EventType",
            "returns",
            "seealso"
        ]
    },
    "Plugins": [
        "../Guilded.Documentation/bin/Release/net6.0/Guilded.Documentation.dll"
    ]
}